{
  "Npcs": [
    {
      "Id": 1,
      "Name": "George",
      "Greeting": "Hello I have been looking for you",
      "Swear": "Damn it!",
      "Description": "Scrawny, short man",
      "Clue": "I would maybe do __ and ___",
      "Goodbye": "Goodbye my friend",
      "Dialogs" : {
        "PathA" : {
          "Prompt": "What the hell have you done!! Now you gotta fix it",
          "MsgA": "Finally, now get out of my sight",
          "MsgB": "Maybe it wasn't so bad that you destroyed it",
          "MsgC": "Alright, go home you'll only make thing worse"
        },
        "MsgB" : "Nice job, clean and simple",
        "MsgC" : "Wow that's a thing I would never ever do in my life. But it works, still"
      }
    },
    {
      "Id": 2,
      "Name": "Dave",
      "Greeting" : "Hi"
    }
  ]
}